./.gitignore
./PKG-INFO
./README.md
./example.md
./pyproject.toml
./pytest.ini
./requirements.txt
./server.py
./uv.lock
./.continue/mcpServers/mcp-server.yaml
./.continue/rules/new-docs-rule.md
./.github/workflows/publish.yml
./.github/workflows/test.yml
./docs/advanced-features.md
./docs/available_tools.md
./docs/getting-started.md
./docs/git-integration.md
./docs/setup-mcp.md
./tests/__init__.py
./tests/conftest.py
./tests/test_simple.py
check_the_docs-0.1.0.dist-info/METADATA
check_the_docs-0.1.0.dist-info/WHEEL
check_the_docs-0.1.0.dist-info/entry_points.txt
check_the_docs-0.1.0.dist-info/RECORD
