Metadata-Version: 2.4
Name: check_the_docs
Version: 0.1.0
Summary: FastMCP server for document indexing and Git diff analysis with ChromaDB
Requires-Python: >=3.10
Requires-Dist: chromadb>=0.4.0
Requires-Dist: fastmcp>=0.1.0
Requires-Dist: gitpython>=3.1.0
Requires-Dist: ollama>=0.1.0
Requires-Dist: pydantic>=2.0.0
